jupyterlab_databrix_homepage/__init__.py
jupyterlab_databrix_homepage/_version.py
jupyterlab_databrix_homepage-0.1.5.data/data/share/jupyter/labextensions/jupyterlab_databrix_homepage/package.json
jupyterlab_databrix_homepage-0.1.5.data/data/share/jupyter/labextensions/jupyterlab_databrix_homepage/static/509.50f4c70f79a3aaefeb23.js
jupyterlab_databrix_homepage-0.1.5.data/data/share/jupyter/labextensions/jupyterlab_databrix_homepage/static/728.d1ff02147025fd0e3244.js
jupyterlab_databrix_homepage-0.1.5.data/data/share/jupyter/labextensions/jupyterlab_databrix_homepage/static/remoteEntry.946f3b408cad22005201.js
jupyterlab_databrix_homepage-0.1.5.data/data/share/jupyter/labextensions/jupyterlab_databrix_homepage/static/style.js
jupyterlab_databrix_homepage-0.1.5.data/data/share/jupyter/labextensions/jupyterlab_databrix_homepage/static/third-party-licenses.json
jupyterlab_databrix_homepage-0.1.5.data/data/share/jupyter/labextensions/jupyterlab_databrix_homepage/install.json
jupyterlab_databrix_homepage-0.1.5.dist-info/METADATA
jupyterlab_databrix_homepage-0.1.5.dist-info/WHEEL
jupyterlab_databrix_homepage-0.1.5.dist-info/licenses/LICENSE
jupyterlab_databrix_homepage-0.1.5.dist-info/RECORD
